db_library/__init__.py
db_library/db_library.py
db_library-0.2.dist-info/METADATA
db_library-0.2.dist-info/WHEEL
db_library-0.2.dist-info/top_level.txt
db_library-0.2.dist-info/RECORD
