Metadata-Version: 2.2
Name: db_library
Version: 0.2
Summary: A library for working with PostgreSQL 2
Author: Alexandr Ignatiev
Author-email: frive9007@gmail.com
Classifier: Programming Language :: Python :: 3
Classifier: License :: OSI Approved :: MIT License
Classifier: Operating System :: OS Independent
Requires-Python: >=3.6
Dynamic: author
Dynamic: author-email
Dynamic: classifier
Dynamic: description-content-type
Dynamic: requires-python
Dynamic: summary
